{
  "name"    : "Apiviewer (export) config",

  "export" : ["source", "build"],

  "jobs" :
  {
    "common" :
    {
      "let" :
      {
        "APIVIEWER_ROOT" : ".",
        "APIVIEWER"      : "apiviewer",
        "APPLICATION"    : "apiviewer",
        "QOOXDOO_PATH"   : "../../framework",
        "QOOXDOO_URI"    : "../${QOOXDOO_PATH}",
        "API_INCLUDE"    : ["*"],
        "API_EXCLUDE"    : [],
        "BUILD_PATH"     : "${APIVIEWER_ROOT}/build",
        "CACHE"          : "../../cache"
      },

      "library" :
      [
        {
          "manifest" : "${QOOXDOO_PATH}/Manifest.json",
          "uri"      : "${QOOXDOO_URI}"
        },

        {
          "manifest" : "${APIVIEWER_ROOT}/Manifest.json",
          "uri"      : ".."
        }
      ],

      "settings" :
      {
        "qx.application"  : "${APIVIEWER}.Application",
        "qx.theme"        : "${APIVIEWER}.Theme",
        "qx.version"      : "0.8"
      },

      "cache" :
      {
        "compile" : "${CACHE}"
      }
    },


    "source-script" :
    {
      "extend" : ["common"],
      "include" : ["${APIVIEWER}.*"],

      "compile-source" :
      {
        "file" : "./source/script/${APIVIEWER}.js",
        "root" : "source"
      }
    },


    "source" :
    {
      "run" :
      [
        "source-script",
        "source-data"
      ]
    },


    "build-script" :
    {
      "extend" : ["common"],
      "include" : ["${APIVIEWER}.*"],
      
      "variants" :
      {
        "qx.aspects" : ["off"],
        "qx.debug" : ["off"]
      },

      "compile-dist" :
      {
        "target" : "${BUILD_PATH}",
        "file" : "${BUILD_PATH}/script/${APIVIEWER}.js",
        "format" : false,
        "optimize" : ["strings", "basecalls", "variables", "privates"],
        "uri"  : "script/${APIVIEWER}.js",
        "root" : "${BUILD_PATH}"
      }
    },


    "build-files" :
    {
      "extend" : ["common"],

      "copy-files" :
      {
        "files" :
        [
          "index.html"
        ],

        "target" : "${BUILD_PATH}",
        "source" : "${APIVIEWER_ROOT}/source"
      }
    },


    "build-resources":
    {
      "extend" : ["common"],
      "include" : ["${APIVIEWER}.*"],

      "copy-resources" :
      {
        "target" : "${BUILD_PATH}"
      }
    },


    "build" :
    {
      "run" :
      [
        "build-resources",
        "build-script",
        "build-files",
        "build-data"
      ]
    },


    "source-data" :
    {
      "extend" : ["common"],

      "include" : "${API_INCLUDE}",
      "exclude" : "${API_EXCLUDE}",

      "api" :
      {
        "path" : "source/script"
      }
    },


    "build-data" :
    {
      "extend" : ["common"],

      "include" : "${API_INCLUDE}",
      "exclude" : "${API_EXCLUDE}",

      "api" :
      {
        "path" : "${BUILD_PATH}/script"
      }
    }
  }
}

